AUTHORS
LICENSE
MANIFEST.in
README.rst
run_tests.py
setup.py
contrib/.gitignore
contrib/README
contrib/Vagrantfile
contrib/aut2simulink.py
contrib/ci_deploy_doc.py
contrib/nonroot-vagrant-instructions.md
contrib/readdstar.py
contrib/readlbt.py
contrib/spin2dstar.py
contrib/test_spin2dstar.py
contrib/AES/AES_specgen.py
contrib/AES/README
contrib/AES/SLD.mat
contrib/AES/topology.jpg
contrib/fmu/Makefile
contrib/fmu/README.rst
contrib/fmu/ctrlexport.py
contrib/fmu/exportFMU.py
contrib/fmu/model.xml
contrib/fmu/poly2str.py
contrib/fmu/pppexport.py
contrib/fmu/robotfmu.py
contrib/fmu/include/FSM.h
contrib/fmu/include/TuLiPControl.h
contrib/fmu/include/data.h
contrib/fmu/include/polytope.h
contrib/fmu/include/pppdata.h
contrib/fmu/sources/FSM.c
contrib/fmu/sources/TuLiPControl.c
contrib/fmu/sources/TuLiPFMU.c
contrib/fmu/sources/polytope.c
contrib/fmu/test/test_controller.c
contrib/fmu/test/test_fsm.c
contrib/logging/howto_use_logging.py
contrib/logging/logging_config.json
contrib/macports/Portfile
contrib/macports/create_local_portfile_repository.sh
contrib/matlabsim/.gitignore
contrib/matlabsim/README
contrib/matlabsim/cont_to_disc.m
contrib/matlabsim/get_input.m
contrib/matlabsim/get_input_switched.m
contrib/matlabsim/load_continuous.m
contrib/matlabsim/load_tulip.m
contrib/matlabsim/notes.md
contrib/matlabsim/tomatlab.py
contrib/matlabsim/continuous_example/continuous.py
contrib/matlabsim/continuous_example/load_robot.m
contrib/matlabsim/discrete_example/discrete.py
contrib/matlabsim/discrete_example/load_discrete.m
contrib/matlabsim/switched_example/double_tank.py
contrib/matlabsim/switched_example/load_switched.m
contrib/mptmodels/mpt2python.m
contrib/mptmodels/mpt2python.py
contrib/nessainstall/README.md
contrib/nessainstall/install.sh
contrib/nessainstall/instructions.md
contrib/parity_games/solve_parity_game.py
contrib/xml/xmlio.py
doc/.gitignore
doc/Makefile
doc/abstracting_dynamics.svg
doc/approach.png
doc/benchmarks.rst
doc/bib.txt
doc/bibliography.rst
tulip.egg-info/PKG-INFO
tulip.egg-info/SOURCES.txt
tulip.egg-info/dependency_links.txt
tulip.egg-info/requires.txt
tulip.egg-info/top_level.txt
